preprokit/__init__.py
preprokit/filters.py
preprokit/utils.py
preprokit/trasformers/__init__.py
preprokit/trasformers/dictT.py
preprokit/trasformers/frameT.py
preprokit/trasformers/listT.py
preprokit/trasformers/ndarrayT.py
preprokit/trasformers/seriesT.py
preprokit-0.1.0.1.dist-info/LICENSE
preprokit-0.1.0.1.dist-info/METADATA
preprokit-0.1.0.1.dist-info/WHEEL
preprokit-0.1.0.1.dist-info/top_level.txt
preprokit-0.1.0.1.dist-info/RECORD
